tisdb/__init__.py
tisdb/api.py
tisdb/client.py
tisdb/config.py
tisdb/errors.py
tisdb/types.py
tisdb/model/__init__.py
tisdb/model/mysql/__init__.py
tisdb-0.0.3.dist-info/METADATA
tisdb-0.0.3.dist-info/WHEEL
tisdb-0.0.3.dist-info/top_level.txt
tisdb-0.0.3.dist-info/RECORD
